LICENSE
MANIFEST.in
README.rst
setup.py
bee_django_track/__init__.py
bee_django_track/admin.py
bee_django_track/apps.py
bee_django_track/decorators.py
bee_django_track/exports.py
bee_django_track/forms.py
bee_django_track/models.py
bee_django_track/tests.py
bee_django_track/urls.py
bee_django_track/utils.py
bee_django_track/views.py
bee_django_track.egg-info/PKG-INFO
bee_django_track.egg-info/SOURCES.txt
bee_django_track.egg-info/dependency_links.txt
bee_django_track.egg-info/top_level.txt
bee_django_track/migrations/0001_initial.py
bee_django_track/migrations/0001_initial.pyc
bee_django_track/migrations/0002_auto_20180810_1846.py
bee_django_track/migrations/0002_auto_20180810_1846.pyc
bee_django_track/migrations/0003_auto_20181031_1530.py
bee_django_track/migrations/0003_auto_20181031_1530.pyc
bee_django_track/migrations/0004_auto_20181031_1533.py
bee_django_track/migrations/0004_auto_20181031_1533.pyc
bee_django_track/migrations/0005_auto_20181031_1534.py
bee_django_track/migrations/0005_auto_20181031_1534.pyc
bee_django_track/migrations/0006_auto_20181109_1336.py
bee_django_track/migrations/0006_auto_20181109_1336.pyc
bee_django_track/migrations/0007_auto_20190918_1510.py
bee_django_track/migrations/0007_auto_20190918_1510.pyc
bee_django_track/migrations/__init__.py
bee_django_track/migrations/__init__.pyc
bee_django_track/static/bee_django_track/bootstrap/css/bootstrap-theme.min.css
bee_django_track/static/bee_django_track/bootstrap/css/bootstrap.min.css
bee_django_track/static/bee_django_track/bootstrap/fonts/glyphicons-halflings-regular.eot
bee_django_track/static/bee_django_track/bootstrap/fonts/glyphicons-halflings-regular.svg
bee_django_track/static/bee_django_track/bootstrap/fonts/glyphicons-halflings-regular.ttf
bee_django_track/static/bee_django_track/bootstrap/fonts/glyphicons-halflings-regular.woff
bee_django_track/static/bee_django_track/bootstrap/fonts/glyphicons-halflings-regular.woff2
bee_django_track/static/bee_django_track/bootstrap/js/bootstrap.min.js
bee_django_track/static/bee_django_track/cityselect/css/main.css
bee_django_track/static/bee_django_track/cityselect/js/city.min.js
